mysqLLL/__init__.py
mysqLLL/__pycache__/__init__.cpython-312.pyc
mysqLLL/connector/__init__.py
mysqLLL/connector/_decorating.py
mysqLLL/connector/_scripting.py
mysqLLL/connector/abstracts.py
mysqLLL/connector/authentication.py
mysqLLL/connector/charsets.py
mysqLLL/connector/connection.py
mysqLLL/connector/connection_cext.py
mysqLLL/connector/constants.py
mysqLLL/connector/conversion.py
mysqLLL/connector/cursor.py
mysqLLL/connector/cursor_cext.py
mysqLLL/connector/custom_types.py
mysqLLL/connector/dbapi.py
mysqLLL/connector/errorcode.py
mysqLLL/connector/errors.py
mysqLLL/connector/logger.py
mysqLLL/connector/network.py
mysqLLL/connector/optionfiles.py
mysqLLL/connector/pooling.py
mysqLLL/connector/protocol.py
mysqLLL/connector/py.typed
mysqLLL/connector/tls_ciphers.py
mysqLLL/connector/types.py
mysqLLL/connector/utils.py
mysqLLL/connector/version.py
mysqLLL/connector/1/__init__.py
mysqLLL/connector/1/auth_client.py
mysqLLL/connector/1/auth_staff.py
mysqLLL/connector/1/db.py
mysqLLL/connector/1/main.py
mysqLLL/connector/1/requirements.txt
mysqLLL/connector/1/screens_admin.py
mysqLLL/connector/1/screens_client.py
mysqLLL/connector/1/screens_manager.py
mysqLLL/connector/1/screens_staff.py
mysqLLL/connector/__pycache__/__init__.cpython-312.pyc
mysqLLL/connector/__pycache__/_decorating.cpython-312.pyc
mysqLLL/connector/__pycache__/_scripting.cpython-312.pyc
mysqLLL/connector/__pycache__/abstracts.cpython-312.pyc
mysqLLL/connector/__pycache__/authentication.cpython-312.pyc
mysqLLL/connector/__pycache__/charsets.cpython-312.pyc
mysqLLL/connector/__pycache__/connection.cpython-312.pyc
mysqLLL/connector/__pycache__/connection_cext.cpython-312.pyc
mysqLLL/connector/__pycache__/constants.cpython-312.pyc
mysqLLL/connector/__pycache__/conversion.cpython-312.pyc
mysqLLL/connector/__pycache__/cursor.cpython-312.pyc
mysqLLL/connector/__pycache__/cursor_cext.cpython-312.pyc
mysqLLL/connector/__pycache__/custom_types.cpython-312.pyc
mysql_conector_python-0.1.6.dist-info/METADATA
mysql_conector_python-0.1.6.dist-info/WHEEL
mysql_conector_python-0.1.6.dist-info/top_level.txt
mysql_conector_python-0.1.6.dist-info/RECORD
